styledlogger/__init__.py
styledlogger/logger.py
styledlogger/classes/__init__.py
styledlogger/classes/callback.py
styledlogger/classes/callbackctx.py
styledlogger/classes/printcolors.py
styledlogger/classes/printtypes.py
styledlogger/classes/styleconfig.py
styledlogger-0.1.4.dist-info/LICENSE
styledlogger-0.1.4.dist-info/METADATA
styledlogger-0.1.4.dist-info/WHEEL
styledlogger-0.1.4.dist-info/top_level.txt
styledlogger-0.1.4.dist-info/RECORD
