Metadata-Version: 2.1
Name: styledlogger
Version: 0.1.4
Summary: A simple, styled logging library.
Home-page: https://github.com/SpLayzDK/StyledLogger/
Author: ImAlek (splayzdk)
Author-email: alek@imalek.me
License: BSL 1.0
Classifier: Programming Language :: Python :: 3
Classifier: License :: OSI Approved :: Boost Software License 1.0 (BSL-1.0)
Classifier: Operating System :: OS Independent
Requires-Python: >=3.7
License-File: LICENSE
Requires-Dist: colorama (>=0.4.6)
Requires-Dist: arrow (>=1.2.3)
Provides-Extra: dev
Requires-Dist: pytest (>=7.0) ; extra == 'dev'
Requires-Dist: twine (>=4.0.2) ; extra == 'dev'
